red_duck-0.1.0.dist-info/METADATA
red_duck-0.1.0.dist-info/WHEEL
red_duck/__init__.py
red_duck/controllers.py
red_duck-0.1.0.dist-info/RECORD
